MANIFEST.in
README.md
setup.cfg
setup.py
harvest/__init__.py
harvest/harvest.py
harvest_python3.egg-info/PKG-INFO
harvest_python3.egg-info/SOURCES.txt
harvest_python3.egg-info/dependency_links.txt
harvest_python3.egg-info/requires.txt
harvest_python3.egg-info/top_level.txt
harvest_python3.egg-info/zip-safe