Metadata-Version: 1.1
Name: harvest-python3
Version: 0.0.3
Summary: Python3 wrapper for harvest API
Home-page: https://github.com/laodicean/harvest-python3
Author: Brendan Roy
Author-email: br3ndanr@gmail.com
License: MIT
Keywords: harvest api harvestapp
Platform: UNKNOWN
Classifier: Development Status :: 3 - Alpha
Classifier: Environment :: Console
Classifier: Intended Audience :: Developers
Classifier: Natural Language :: English
Classifier: Programming Language :: Python :: 3
Classifier: Topic :: Software Development :: Libraries
